MANIFEST.in
README.txt
setup.cfg
setup.py
PayPy.egg-info/PKG-INFO
PayPy.egg-info/SOURCES.txt
PayPy.egg-info/dependency_links.txt
PayPy.egg-info/not-zip-safe
PayPy.egg-info/requires.txt
PayPy.egg-info/top_level.txt
docs/index.txt
docs/payments.txt
docs/subscriptions.txt
paypy/__init__.py
paypy/payment.py
paypy/profile.py
paypy/subscription.py
paypy/adapters/__init__.py
paypy/adapters/authnet/__init__.py
paypy/adapters/authnet/aim.py
paypy/adapters/authnet/arb.py
paypy/adapters/authnet/cim.py
paypy/adapters/google/__init__.py
paypy/adapters/google/checkout.py
paypy/exceptions/__init__.py
paypy/exceptions/authnet.py
paypy/exceptions/payment.py
paypy/exceptions/profile.py
paypy/exceptions/subscription.py
paypy/schemas/__init__.py
paypy/schemas/address.py
paypy/schemas/billing.py
paypy/schemas/payment.py
paypy/schemas/shipping.py
paypy/schemas/transaction.py
paypy/schemas/authnet/__init__.py
paypy/schemas/authnet/aim.py
paypy/schemas/authnet/arb.py
paypy/schemas/authnet/cim.py
paypy/schemas/google/__init__.py
paypy/schemas/google/checkout.py
paypy/serializers/__init__.py
paypy/serializers/authnet/__init__.py
paypy/serializers/authnet/aim.py
paypy/serializers/authnet/arb.py
paypy/serializers/authnet/cim.py
tests/__init__.py
tests/test_payment.py
tests/test_profile.py
tests/test_subscription.py