Metadata-Version: 1.0
Name: PayPy
Version: 0.5.9
Summary: Payment gateway API integration package
Home-page: http://bitbucket.org/ixmatus/paypy
Author: Parnell Springmeyer
Author-email: ixmatus@gmail.com
License: PSF
Platform: UNKNOWN
Classifier: Intended Audience :: Developers
Classifier: License :: OSI Approved :: Python Software Foundation License
Classifier: Programming Language :: Python
Classifier: Topic :: Software Development :: Libraries :: Python Modules
